[
    {
        "experiment":"mml06",
        "acte":1,
        "scene":1,
        "version":"modern",
        "chunk":0,
        "verse_id":1,
        "char":"SGANARELLE",
        "text":"Non, je ne veux pas faire ce que tu me demandes. C'est à moi de décider et d'être le chef ici.",
        "selected":1
    },
    {
        "experiment":"mml07",
        "acte":1,
        "scene":1,
        "version":"modern",
        "chunk":0,
        "verse_id":1,
        "char":"SGANARELLE",
        "text":"Non, je te dis que je ne veux rien faire de cela, et que c'est à moi de parler et d'être le chef.",
        "selected":0
    },
    {
        "experiment":"mml06",
        "acte":1,
        "scene":1,
        "version":"original",
        "chunk":0,
        "verse_id":1,
        "char":"SGANARELLE",
        "text":"NON, je te dis que je n'en veux rien faire, et que c'est à moi de parler et d'être le maître.",
        "selected":0
    },
    {
        "experiment":"mml06",
        "acte":1,
        "scene":1,
        "version":"modern",
        "chunk":0,
        "verse_id":2,
        "char":"MARTINE",
        "text":"Mais moi, je veux que tu fasses ce que je te dis. Je ne me suis pas mariée avec toi pour supporter tes bêtises.",
        "selected":1
    },
    {
        "experiment":"mml07",
        "acte":1,
        "scene":1,
        "version":"modern",
        "chunk":0,
        "verse_id":2,
        "char":"MARTINE",
        "text":"Et je te dis, moi, que je veux que tu vives selon mes envies, et que je ne me suis pas mariée avec toi pour supporter tes bêtises.",
        "selected":0
    },
    {
        "experiment":"mml06",
        "acte":1,
        "scene":1,
        "version":"original",
        "chunk":0,
        "verse_id":2,
        "char":"MARTINE",
        "text":"Et je te dis, moi, que je veux que tu vives à ma fantaisie, et que je ne me suis point mariée avec toi pour souffrir tes fredaines.",
        "selected":0
    },
    {
        "experiment":"mml06",
        "acte":1,
        "scene":1,
        "version":"modern",
        "chunk":0,
        "verse_id":3,
        "char":"SGANARELLE",
        "text":"Ah, quelle corvée d'avoir une femme! Aristote avait raison quand il disait qu'une femme est pire qu'un démon!",
        "selected":1
    },
    {
        "experiment":"mml07",
        "acte":1,
        "scene":1,
        "version":"modern",
        "chunk":0,
        "verse_id":3,
        "char":"SGANARELLE",
        "text":"Quelle corvée d'avoir une femme ! Et Aristote a bien raison quand il dit qu'une femme est pire qu'un démon !",
        "selected":0
    },
    {
        "experiment":"mml06",
        "acte":1,
        "scene":1,
        "version":"original",
        "chunk":0,
        "verse_id":3,
        "char":"SGANARELLE",
        "text":"O la grande fatigue que d'avoir une femme! et qu'Aristote a bien raison quand il dit qu'une femme est pire qu'un démon!",
        "selected":0
    },
    {
        "experiment":"mml06",
        "acte":1,
        "scene":1,
        "version":"modern",
        "chunk":0,
        "verse_id":4,
        "char":"MARTINE",
        "text":"Regardez cet homme intelligent, qui croit tout savoir grâce à son cher Aristote!",
        "selected":0
    },
    {
        "experiment":"mml07",
        "acte":1,
        "scene":1,
        "version":"modern",
        "chunk":0,
        "verse_id":4,
        "char":"MARTINE",
        "text":"Regarde un peu cet homme intelligent, avec son stupide Aristote !",
        "selected":0
    },
    {
        "experiment":"mml_manual",
        "acte":1,
        "scene":1,
        "version":"modern",
        "chunk":0,
        "verse_id":4,
        "char":"MARTINE",
        "text":"Regardez un peu cet homme intelligent, avec son stupide Aristote !",
        "selected":1
    },
    {
        "experiment":"mml06",
        "acte":1,
        "scene":1,
        "version":"original",
        "chunk":0,
        "verse_id":4,
        "char":"MARTINE",
        "text":"Voyez un peu l'habile homme, avec son benêt d'Aristote!",
        "selected":0
    },
    {
        "experiment":"mml06",
        "acte":1,
        "scene":1,
        "version":"modern",
        "chunk":0,
        "verse_id":5,
        "char":"SGANARELLE",
        "text":"Oui, je suis intelligent. Trouvez-moi un bûcheron qui puisse raisonner comme moi, qui ait travaillé six ans pour un célèbre médecin et qui ait appris les bases par cœur dès son plus jeune âge.",
        "selected":0
    },
    {
        "experiment":"mml07",
        "acte":1,
        "scene":1,
        "version":"modern",
        "chunk":0,
        "verse_id":5,
        "char":"SGANARELLE",
        "text":"Oui, un homme intelligent. Trouve-moi un bûcheron qui sache, comme moi, réfléchir sur les choses, qui ait travaillé six ans pour un célèbre médecin, et qui ait appris par cœur les bases de son métier dès son jeune âge.",
        "selected":0
    },
    {
        "experiment":"mml_manual",
        "acte":1,
        "scene":1,
        "version":"modern",
        "chunk":0,
        "verse_id":5,
        "char":"SGANARELLE",
        "text":"Oui, je suis intelligent. Trouve-moi un bûcheron qui puisse raisonner comme moi, qui a travaillé six ans pour un célèbre médecin et qui a appris les bases de son métier par cœur dès son plus jeune âge.",
        "selected":1
    },
    {
        "experiment":"mml06",
        "acte":1,
        "scene":1,
        "version":"original",
        "chunk":0,
        "verse_id":5,
        "char":"SGANARELLE",
        "text":"Oui, habile homme. Trouve-moi un faiseur de fagots qui sache, comme moi, raisonner des choses, qui ait servi six ans un fameux médecin, et qui ait su dans son jeune âge son rudiment par coeur.",
        "selected":0
    },
    {
        "experiment":"mml06",
        "acte":1,
        "scene":1,
        "version":"modern",
        "chunk":0,
        "verse_id":6,
        "char":"MARTINE",
        "text":"Quel fou!",
        "selected":1
    },
    {
        "experiment":"mml06",
        "acte":1,
        "scene":1,
        "version":"modern",
        "chunk":1,
        "verse_id":6,
        "char":"MARTINE",
        "text":"Tu es vraiment un fou!",
        "selected":0
    },
    {
        "experiment":"mml07",
        "acte":1,
        "scene":1,
        "version":"modern",
        "chunk":0,
        "verse_id":6,
        "char":"MARTINE",
        "text":"Quel idiot fin !",
        "selected":0
    },
    {
        "experiment":"mml_manual",
        "acte":1,
        "scene":1,
        "version":"modern",
        "chunk":0,
        "verse_id":6,
        "char":"MARTINE",
        "text":"Quel con!",
        "selected":0
    },
    {
        "experiment":"mml06",
        "acte":1,
        "scene":1,
        "version":"original",
        "chunk":0,
        "verse_id":6,
        "char":"MARTINE",
        "text":"Peste du fou fieffé!",
        "selected":0
    },
    {
        "experiment":"mml06",
        "acte":1,
        "scene":1,
        "version":"modern",
        "chunk":0,
        "verse_id":7,
        "char":"SGANARELLE",
        "text":"Quelle peste!",
        "selected":0
    },
    {
        "experiment":"mml06",
        "acte":1,
        "scene":1,
        "version":"modern",
        "chunk":1,
        "verse_id":7,
        "char":"SGANARELLE",
        "text":"Tu es une carogne!",
        "selected":0
    },
    {
        "experiment":"mml07",
        "acte":1,
        "scene":1,
        "version":"modern",
        "chunk":0,
        "verse_id":7,
        "char":"SGANARELLE",
        "text":"Quelle garce !",
        "selected":0
    },
    {
        "experiment":"mml_manual",
        "acte":1,
        "scene":1,
        "version":"modern",
        "chunk":0,
        "verse_id":7,
        "char":"SGANARELLE",
        "text":"Quelle mégère!",
        "selected":1
    },
    {
        "experiment":"mml06",
        "acte":1,
        "scene":1,
        "version":"original",
        "chunk":0,
        "verse_id":7,
        "char":"SGANARELLE",
        "text":"Peste de la carogne!",
        "selected":0
    },
    {
        "experiment":"mml06",
        "acte":1,
        "scene":1,
        "version":"modern",
        "chunk":0,
        "verse_id":8,
        "char":"MARTINE",
        "text":"Je regrette le jour où j'ai accepté de t'épouser!",
        "selected":0
    },
    {
        "experiment":"mml06",
        "acte":1,
        "scene":1,
        "version":"modern",
        "chunk":1,
        "verse_id":8,
        "char":"MARTINE",
        "text":"Je regrette le jour où j'ai accepté de t'épouser!",
        "selected":0
    },
    {
        "experiment":"mml07",
        "acte":1,
        "scene":1,
        "version":"modern",
        "chunk":0,
        "verse_id":8,
        "char":"MARTINE",
        "text":"Que maudite soit l'heure et le jour où j'ai accepté de dire oui !",
        "selected":0
    },
    {
        "experiment":"mml_manual",
        "acte":1,
        "scene":1,
        "version":"modern",
        "chunk":0,
        "verse_id":8,
        "char":"MARTINE",
        "text":"Maudit soit le jour où j'ai accepté de t'épouser",
        "selected":1
    },
    {
        "experiment":"mml06",
        "acte":1,
        "scene":1,
        "version":"original",
        "chunk":0,
        "verse_id":8,
        "char":"MARTINE",
        "text":"Que maudit soit l'heure et le jour où je m'avisai d'aller dire oui!",
        "selected":0
    },
    {
        "experiment":"mml06",
        "acte":1,
        "scene":1,
        "version":"modern",
        "chunk":0,
        "verse_id":9,
        "char":"SGANARELLE",
        "text":"Je maudis le notaire qui m'a fait signer ce contrat de mariage!",
        "selected":0
    },
    {
        "experiment":"mml06",
        "acte":1,
        "scene":1,
        "version":"modern",
        "chunk":1,
        "verse_id":9,
        "char":"SGANARELLE",
        "text":"Je regrette d'avoir signé ce contrat de mariage qui m'a ruiné!",
        "selected":0
    },
    {
        "experiment":"mml07",
        "acte":1,
        "scene":1,
        "version":"modern",
        "chunk":0,
        "verse_id":9,
        "char":"SGANARELLE",
        "text":"Que maudit soit le notaire aux cornes qui m'a fait signer ma ruine !",
        "selected":0
    },
    {
        "experiment":"mml_manual",
        "acte":1,
        "scene":1,
        "version":"modern",
        "chunk":0,
        "verse_id":9,
        "char":"SGANARELLE",
        "text":"Maudit soit le notaire",
        "selected":0
    },
    {
        "experiment":"mml_manual",
        "acte":1,
        "scene":1,
        "version":"modern",
        "chunk":0,
        "verse_id":9,
        "char":"SGANARELLE",
        "text":"Maudit soit le notaire qui m'a fait signer ce mariage ruineux!",
        "selected":1
    },
    {
        "experiment":"mml06",
        "acte":1,
        "scene":1,
        "version":"original",
        "chunk":0,
        "verse_id":9,
        "char":"SGANARELLE",
        "text":"Que maudit soit le bec cornu de notaire qui me fit signer ma ruine!",
        "selected":0
    },
    {
        "experiment":"mml06",
        "acte":1,
        "scene":1,
        "version":"modern",
        "chunk":0,
        "verse_id":10,
        "char":"MARTINE",
        "text":"Tu devrais être reconnaissant d'avoir une femme comme moi. Tu ne méritais pas de m'épouser!",
        "selected":1
    },
    {
        "experiment":"mml06",
        "acte":1,
        "scene":1,
        "version":"modern",
        "chunk":1,
        "verse_id":10,
        "char":"MARTINE",
        "text":"Tu devrais être reconnaissant d'avoir une femme comme moi!",
        "selected":0
    },
    {
        "experiment":"mml07",
        "acte":1,
        "scene":1,
        "version":"modern",
        "chunk":0,
        "verse_id":10,
        "char":"MARTINE",
        "text":"C'est bien à toi de te plaindre de cette situation ! Ne devrais-tu pas être reconnaissant à Dieu de m'avoir comme femme ? Et mérites-tu d'épouser quelqu'un comme moi ?",
        "selected":0
    },
    {
        "experiment":"mml07",
        "acte":1,
        "scene":1,
        "version":"modern",
        "chunk":1,
        "verse_id":10,
        "char":"MARTINE",
        "text":"Franchement, tu n'as aucune raison de te plaindre de cette situation ! Devrais-tu ne serait-ce qu'un instant cesser de remercier le Ciel de m'avoir comme épouse ? Et mérites-tu d'épouser quelqu'un comme moi ?",
        "selected":0
    },
    {
        "experiment":"mml06",
        "acte":1,
        "scene":1,
        "version":"original",
        "chunk":0,
        "verse_id":10,
        "char":"MARTINE",
        "text":"C'est bien à toi vraiment à te plaindre de cette affaire! Devrois-tu être un seul moment sans rendre grâce au Ciel de m'avoir pour ta femme? et méritois-tu d'épouser une personne comme moi?",
        "selected":0
    },
    {
        "experiment":"mml06",
        "acte":1,
        "scene":1,
        "version":"modern",
        "chunk":1,
        "verse_id":11,
        "char":"SGANARELLE",
        "text":"C'est vrai que tu m'as fait beaucoup d'honneur en m'épousant, mais je ne veux pas en parler.",
        "selected":0
    },
    {
        "experiment":"mml06",
        "acte":1,
        "scene":1,
        "version":"modern",
        "chunk":2,
        "verse_id":11,
        "char":"SGANARELLE",
        "text":"Tu sais, la première nuit de nos noces, j'étais très flatté de ton attention envers moi. Mais bon, oublions ça. Je pourrais dire certaines choses...",
        "selected":0
    },
    {
        "experiment":"mml07",
        "acte":1,
        "scene":1,
        "version":"modern",
        "chunk":0,
        "verse_id":11,
        "char":"SGANARELLE",
        "text":"Il est vrai que tu m'as fait beaucoup d'honneur et que j'ai eu de quoi me vanter la première nuit de nos noces. Hé ! bon sang ! ne me fais pas parler de ça, je dirais certaines choses...",
        "selected":0
    },
    {
        "experiment":"mml07",
        "acte":1,
        "scene":1,
        "version":"modern",
        "chunk":1,
        "verse_id":11,
        "char":"SGANARELLE",
        "text":"Il est vrai que tu m'as fait beaucoup d'honneur et que j'ai eu de quoi me vanter lors de notre première nuit de mariage. Hé ! bon sang ! ne me fais pas parler de ça, je pourrais dire certaines choses...",
        "selected":1
    },
    {
        "experiment":"mml06",
        "acte":1,
        "scene":1,
        "version":"original",
        "chunk":1,
        "verse_id":11,
        "char":"SGANARELLE",
        "text":"Il est vrai que tu me fis trop d'honneur et que j'eus lieu de me louer la première nuit de nos noces. Hé! morbleu! ne me fais point parler là-dessus, je dirois de certaines choses...",
        "selected":0
    },
    {
        "experiment":"mml06",
        "acte":1,
        "scene":1,
        "version":"modern",
        "chunk":1,
        "verse_id":12,
        "char":"MARTINE",
        "text":"Pourquoi?",
        "selected":0
    },
    {
        "experiment":"mml06",
        "acte":1,
        "scene":1,
        "version":"modern",
        "chunk":2,
        "verse_id":12,
        "char":"MARTINE",
        "text":"Quoi donc?",
        "selected":0
    },
    {
        "experiment":"mml07",
        "acte":1,
        "scene":1,
        "version":"modern",
        "chunk":0,
        "verse_id":12,
        "char":"MARTINE",
        "text":"Quoi ? Que dirais-tu ?",
        "selected":1
    },
    {
        "experiment":"mml07",
        "acte":1,
        "scene":1,
        "version":"modern",
        "chunk":1,
        "verse_id":12,
        "char":"MARTINE",
        "text":"Quoi ? Que pourrais-tu dire ?",
        "selected":0
    },
    {
        "experiment":"mml06",
        "acte":1,
        "scene":1,
        "version":"original",
        "chunk":1,
        "verse_id":12,
        "char":"MARTINE",
        "text":"Quoi? que dirois-tu?",
        "selected":0
    },
    {
        "experiment":"mml06",
        "acte":1,
        "scene":1,
        "version":"modern",
        "chunk":1,
        "verse_id":13,
        "char":"SGANARELLE",
        "text":"Laissons ça de côté. Ce qui compte, c'est que tu as de la chance de m'avoir.",
        "selected":1
    },
    {
        "experiment":"mml06",
        "acte":1,
        "scene":1,
        "version":"modern",
        "chunk":2,
        "verse_id":13,
        "char":"SGANARELLE",
        "text":"Peu importe. L'important c'est que nous savons tous les deux que tu as eu de la chance de m'avoir.",
        "selected":0
    },
    {
        "experiment":"mml07",
        "acte":1,
        "scene":1,
        "version":"modern",
        "chunk":0,
        "verse_id":13,
        "char":"SGANARELLE",
        "text":"Laisse tomber ce sujet ; il suffit que nous savons ce que nous savons, et que tu as été bien chanceuse de me trouver.",
        "selected":0
    },
    {
        "experiment":"mml07",
        "acte":1,
        "scene":1,
        "version":"modern",
        "chunk":1,
        "verse_id":13,
        "char":"SGANARELLE",
        "text":"Bon, laissons ce sujet de côté ; il suffit que nous sachions ce que nous savons, et que tu as été bien chanceuse de me trouver.",
        "selected":0
    },
    {
        "experiment":"mml06",
        "acte":1,
        "scene":1,
        "version":"original",
        "chunk":1,
        "verse_id":13,
        "char":"SGANARELLE",
        "text":"Baste! laissons là ce chapitre; il suffit que nous savons ce que nous savons, et que tu fus bien heureuse de me trouver.",
        "selected":0
    },
    {
        "experiment":"mml06",
        "acte":1,
        "scene":1,
        "version":"modern",
        "chunk":1,
        "verse_id":14,
        "char":"MARTINE",
        "text":"De la chance? Tu me mènes à la ruine, tu es un débauché et un traître qui me vole tout!",
        "selected":0
    },
    {
        "experiment":"mml06",
        "acte":1,
        "scene":1,
        "version":"modern",
        "chunk":2,
        "verse_id":14,
        "char":"MARTINE",
        "text":"Comment peux-tu dire que j'ai eu de la chance de t'avoir? Tu m'as ruinée, tu es un ivrogne, un menteur, tu manges tout ce que j'ai...",
        "selected":1
    },
    {
        "experiment":"mml07",
        "acte":1,
        "scene":1,
        "version":"modern",
        "chunk":0,
        "verse_id":14,
        "char":"MARTINE",
        "text":"Comment peux-tu dire que j'ai été chanceuse de te trouver ? Un homme qui me mène à la ruine, un débauché, un traître qui me prend tout ce que j'ai...",
        "selected":0
    },
    {
        "experiment":"mml07",
        "acte":1,
        "scene":1,
        "version":"modern",
        "chunk":1,
        "verse_id":14,
        "char":"MARTINE",
        "text":"Comment ça, bien chanceuse de te trouver ? Un homme qui me mène à la ruine, un débauché, un traître qui me mange tout ce que j'ai...",
        "selected":0
    },
    {
        "experiment":"mml_manual",
        "acte":1,
        "scene":1,
        "version":"modern",
        "chunk":0,
        "verse_id":14,
        "char":"MARTINE",
        "text":"Comment peux-tu dire que j'ai eu de la chance de te trouver ? Tu m'as ruinée, tu es un ivrogne, un menteur qui manges tout ce que j'ai...",
        "selected":1
    },
    {
        "experiment":"mml06",
        "acte":1,
        "scene":1,
        "version":"original",
        "chunk":1,
        "verse_id":14,
        "char":"MARTINE",
        "text":"Qu'appelles-tu bien heureuse de te trouver? Un homme qui me réduit à l'hôpital, un débauché, un traître qui me mange tout ce que j'ai...",
        "selected":0
    },
    {
        "experiment":"mml06",
        "acte":1,
        "scene":1,
        "version":"modern",
        "chunk":1,
        "verse_id":15,
        "char":"SGANARELLE",
        "text":"Tu mens, je ne te vole qu'une partie de ce que tu as.",
        "selected":0
    },
    {
        "experiment":"mml06",
        "acte":1,
        "scene":1,
        "version":"modern",
        "chunk":2,
        "verse_id":15,
        "char":"SGANARELLE",
        "text":"Tu mens, j'en bois seulement une partie.",
        "selected":0
    },
    {
        "experiment":"mml07",
        "acte":1,
        "scene":1,
        "version":"modern",
        "chunk":0,
        "verse_id":15,
        "char":"SGANARELLE",
        "text":"Tu mens, j'en bois une partie.",
        "selected":1
    },
    {
        "experiment":"mml06",
        "acte":1,
        "scene":1,
        "version":"original",
        "chunk":1,
        "verse_id":15,
        "char":"SGANARELLE",
        "text":"Tu as menti, j'en bois une partie.",
        "selected":0
    },
    {
        "experiment":"mml06",
        "acte":1,
        "scene":1,
        "version":"modern",
        "chunk":2,
        "verse_id":16,
        "char":"MARTINE",
        "text":"Tu vends tout ce qui se trouve dans la maison...",
        "selected":1
    },
    {
        "experiment":"mml06",
        "acte":1,
        "scene":1,
        "version":"modern",
        "chunk":3,
        "verse_id":16,
        "char":"MARTINE",
        "text":"Qui vend tout ce qui est dans la maison petit à petit...",
        "selected":0
    },
    {
        "experiment":"mml07",
        "acte":1,
        "scene":1,
        "version":"modern",
        "chunk":0,
        "verse_id":16,
        "char":"MARTINE",
        "text":"Qui vend petit à petit tout ce qui se trouve dans la maison...",
        "selected":0
    },
    {
        "experiment":"mml06",
        "acte":1,
        "scene":1,
        "version":"original",
        "chunk":2,
        "verse_id":16,
        "char":"MARTINE",
        "text":"Qui me vend pièce à pièce tout ce qui est dans le logis...",
        "selected":0
    },
    {
        "experiment":"mml06",
        "acte":1,
        "scene":1,
        "version":"modern",
        "chunk":2,
        "verse_id":17,
        "char":"SGANARELLE",
        "text":"C'est ce qu'on appelle vivre modestement.",
        "selected":1
    },
    {
        "experiment":"mml06",
        "acte":1,
        "scene":1,
        "version":"modern",
        "chunk":3,
        "verse_id":17,
        "char":"SGANARELLE",
        "text":"C'est une façon de vivre ensemble.",
        "selected":0
    },
    {
        "experiment":"mml07",
        "acte":1,
        "scene":1,
        "version":"modern",
        "chunk":0,
        "verse_id":17,
        "char":"SGANARELLE",
        "text":"C'est la vie de couple.",
        "selected":0
    },
    {
        "experiment":"mml07",
        "acte":1,
        "scene":1,
        "version":"modern",
        "chunk":1,
        "verse_id":17,
        "char":"SGANARELLE",
        "text":"C'est vivre en faisant des économies.",
        "selected":0
    },
    {
        "experiment":"mml06",
        "acte":1,
        "scene":1,
        "version":"original",
        "chunk":2,
        "verse_id":17,
        "char":"SGANARELLE",
        "text":"C'est vivre de ménage.",
        "selected":0
    },
    {
        "experiment":"mml06",
        "acte":1,
        "scene":1,
        "version":"modern",
        "chunk":2,
        "verse_id":18,
        "char":"MARTINE",
        "text":"Tu as même pris mon lit...",
        "selected":1
    },
    {
        "experiment":"mml06",
        "acte":1,
        "scene":1,
        "version":"modern",
        "chunk":3,
        "verse_id":18,
        "char":"MARTINE",
        "text":"Qui m'a même pris mon lit...",
        "selected":0
    },
    {
        "experiment":"mml07",
        "acte":1,
        "scene":1,
        "version":"modern",
        "chunk":0,
        "verse_id":18,
        "char":"MARTINE",
        "text":"Qui m'a même enlevé le lit que j'avais...",
        "selected":0
    },
    {
        "experiment":"mml06",
        "acte":1,
        "scene":1,
        "version":"original",
        "chunk":2,
        "verse_id":18,
        "char":"MARTINE",
        "text":"Qui m'a ôté jusqu'au lit que j'avois...",
        "selected":0
    },
    {
        "experiment":"mml06",
        "acte":1,
        "scene":1,
        "version":"modern",
        "chunk":2,
        "verse_id":19,
        "char":"SGANARELLE",
        "text":"Tu te lèveras plus tard.",
        "selected":0
    },
    {
        "experiment":"mml06",
        "acte":1,
        "scene":1,
        "version":"modern",
        "chunk":3,
        "verse_id":19,
        "char":"SGANARELLE",
        "text":"Tu ne te lèveras plus tôt.",
        "selected":0
    },
    {
        "experiment":"mml07",
        "acte":1,
        "scene":1,
        "version":"modern",
        "chunk":1,
        "verse_id":19,
        "char":"SGANARELLE",
        "text":"Tu te lèveras plus tard.",
        "selected":0
    },
    {
        "experiment":"mml07",
        "acte":1,
        "scene":1,
        "version":"modern",
        "chunk":2,
        "verse_id":19,
        "char":"SGANARELLE",
        "text":"Tu ne te lèveras plus tôt le matin.",
        "selected":0
    },
    {
        "experiment":"mml_manual",
        "acte":1,
        "scene":1,
        "version":"modern",
        "chunk":0,
        "verse_id":19,
        "char":"SGANARELLE",
        "text":"Tu te lèveras plus tôt.",
        "selected":1
    },
    {
        "experiment":"mml06",
        "acte":1,
        "scene":1,
        "version":"original",
        "chunk":2,
        "verse_id":19,
        "char":"SGANARELLE",
        "text":"Tu t'en lèveras plus matin.",
        "selected":0
    },
    {
        "experiment":"mml06",
        "acte":1,
        "scene":1,
        "version":"modern",
        "chunk":2,
        "verse_id":20,
        "char":"MARTINE",
        "text":"Et tu as vendu tous les meubles de la maison...",
        "selected":1
    },
    {
        "experiment":"mml06",
        "acte":1,
        "scene":1,
        "version":"modern",
        "chunk":3,
        "verse_id":20,
        "char":"MARTINE",
        "text":"Et qui ne laisse aucun meuble dans la maison...",
        "selected":0
    },
    {
        "experiment":"mml07",
        "acte":1,
        "scene":1,
        "version":"modern",
        "chunk":1,
        "verse_id":20,
        "char":"MARTINE",
        "text":"Enfin, qui ne laisse aucun meuble dans toute la maison...",
        "selected":0
    },
    {
        "experiment":"mml07",
        "acte":1,
        "scene":1,
        "version":"modern",
        "chunk":2,
        "verse_id":20,
        "char":"MARTINE",
        "text":"Enfin, tu ne laisses aucun meuble dans toute la maison...",
        "selected":0
    },
    {
        "experiment":"mml06",
        "acte":1,
        "scene":1,
        "version":"original",
        "chunk":2,
        "verse_id":20,
        "char":"MARTINE",
        "text":"Enfin, qui ne laisse aucun meuble dans toute la maison...",
        "selected":0
    },
    {
        "experiment":"mml06",
        "acte":1,
        "scene":1,
        "version":"modern",
        "chunk":3,
        "verse_id":21,
        "char":"SGANARELLE",
        "text":"C'est plus facile pour déménager.",
        "selected":1
    },
    {
        "experiment":"mml06",
        "acte":1,
        "scene":1,
        "version":"modern",
        "chunk":4,
        "verse_id":21,
        "char":"SGANARELLE",
        "text":"On peut déménager plus facilement.",
        "selected":0
    },
    {
        "experiment":"mml07",
        "acte":1,
        "scene":1,
        "version":"modern",
        "chunk":1,
        "verse_id":21,
        "char":"SGANARELLE",
        "text":"On déménage plus facilement.",
        "selected":0
    },
    {
        "experiment":"mml06",
        "acte":1,
        "scene":1,
        "version":"original",
        "chunk":3,
        "verse_id":21,
        "char":"SGANARELLE",
        "text":"On en déménage plus aisément.",
        "selected":0
    },
    {
        "experiment":"mml06",
        "acte":1,
        "scene":1,
        "version":"modern",
        "chunk":3,
        "verse_id":22,
        "char":"MARTINE",
        "text":"Et qui passe son temps à jouer et boire...",
        "selected":1
    },
    {
        "experiment":"mml06",
        "acte":1,
        "scene":1,
        "version":"modern",
        "chunk":4,
        "verse_id":22,
        "char":"MARTINE",
        "text":"Tu passes tes journées à jouer et à boire.",
        "selected":0
    },
    {
        "experiment":"mml07",
        "acte":1,
        "scene":1,
        "version":"modern",
        "chunk":1,
        "verse_id":22,
        "char":"MARTINE",
        "text":"Et qui, du matin au soir, ne fait que jouer et boire.",
        "selected":0
    },
    {
        "experiment":"mml07",
        "acte":1,
        "scene":1,
        "version":"modern",
        "chunk":2,
        "verse_id":22,
        "char":"MARTINE",
        "text":"Et tu passes ton temps à jouer et à boire du matin au soir.",
        "selected":0
    },
    {
        "experiment":"mml06",
        "acte":1,
        "scene":1,
        "version":"original",
        "chunk":3,
        "verse_id":22,
        "char":"MARTINE",
        "text":"Et qui, du matin jusqu'au soir, ne fait que jouer et que boire.",
        "selected":0
    },
    {
        "experiment":"mml06",
        "acte":1,
        "scene":1,
        "version":"modern",
        "chunk":3,
        "verse_id":23,
        "char":"SGANARELLE",
        "text":"Pour ne pas m'ennuyer.",
        "selected":0
    },
    {
        "experiment":"mml06",
        "acte":1,
        "scene":1,
        "version":"modern",
        "chunk":4,
        "verse_id":23,
        "char":"SGANARELLE",
        "text":"C'est pour ne pas m'ennuyer.",
        "selected":1
    },
    {
        "experiment":"mml07",
        "acte":1,
        "scene":1,
        "version":"modern",
        "chunk":1,
        "verse_id":23,
        "char":"SGANARELLE",
        "text":"C'est pour ne pas m'ennuyer.",
        "selected":0
    },
    {
        "experiment":"mml06",
        "acte":1,
        "scene":1,
        "version":"original",
        "chunk":3,
        "verse_id":23,
        "char":"SGANARELLE",
        "text":"C'est pour ne me point ennuyer.",
        "selected":0
    },
    {
        "experiment":"mml06",
        "acte":1,
        "scene":1,
        "version":"modern",
        "chunk":3,
        "verse_id":24,
        "char":"MARTINE",
        "text":"Et que dois-je faire avec ma famille pendant ce temps?",
        "selected":0
    },
    {
        "experiment":"mml06",
        "acte":1,
        "scene":1,
        "version":"modern",
        "chunk":4,
        "verse_id":24,
        "char":"MARTINE",
        "text":"Et pendant ce temps, que dois-je faire avec ma famille?",
        "selected":0
    },
    {
        "experiment":"mml07",
        "acte":1,
        "scene":1,
        "version":"modern",
        "chunk":1,
        "verse_id":24,
        "char":"MARTINE",
        "text":"Et que veux-tu que je fasse avec ma famille pendant ce temps ?",
        "selected":1
    },
    {
        "experiment":"mml07",
        "acte":1,
        "scene":1,
        "version":"modern",
        "chunk":2,
        "verse_id":24,
        "char":"MARTINE",
        "text":"Et pendant ce temps, que veux-tu que je fasse avec ma famille?",
        "selected":0
    },
    {
        "experiment":"mml06",
        "acte":1,
        "scene":1,
        "version":"original",
        "chunk":3,
        "verse_id":24,
        "char":"MARTINE",
        "text":"Et que veux-tu, pendant ce temps, que je fasse avec ma famille?",
        "selected":0
    },
    {
        "experiment":"mml06",
        "acte":1,
        "scene":1,
        "version":"modern",
        "chunk":3,
        "verse_id":25,
        "char":"SGANARELLE",
        "text":"Tout ce que tu veux.",
        "selected":1
    },
    {
        "experiment":"mml06",
        "acte":1,
        "scene":1,
        "version":"modern",
        "chunk":4,
        "verse_id":25,
        "char":"SGANARELLE",
        "text":"Tout ce que tu veux.",
        "selected":0
    },
    {
        "experiment":"mml06",
        "acte":1,
        "scene":1,
        "version":"original",
        "chunk":3,
        "verse_id":25,
        "char":"SGANARELLE",
        "text":"Tout ce qu'il te plaira.",
        "selected":0
    },
    {
        "experiment":"mml06",
        "acte":1,
        "scene":1,
        "version":"modern",
        "chunk":4,
        "verse_id":26,
        "char":"MARTINE",
        "text":"J'ai quatre petits enfants qui ont faim tout le temps.",
        "selected":0
    },
    {
        "experiment":"mml06",
        "acte":1,
        "scene":1,
        "version":"modern",
        "chunk":5,
        "verse_id":26,
        "char":"MARTINE",
        "text":"J'ai quatre petits enfants à charge.",
        "selected":0
    },
    {
        "experiment":"mml06",
        "acte":1,
        "scene":1,
        "version":"original",
        "chunk":4,
        "verse_id":26,
        "char":"MARTINE",
        "text":"J'ai quatre pauvres petits enfants sur les bras.",
        "selected":1
    },
    {
        "experiment":"mml06",
        "acte":1,
        "scene":1,
        "version":"modern",
        "chunk":4,
        "verse_id":27,
        "char":"SGANARELLE",
        "text":"Donne-leur une fessée. Quand j'ai bien mangé et bu, je veux que tout le monde soit heureux dans ma maison.",
        "selected":0
    },
    {
        "experiment":"mml06",
        "acte":1,
        "scene":1,
        "version":"modern",
        "chunk":5,
        "verse_id":27,
        "char":"SGANARELLE",
        "text":"Pose-les par terre.",
        "selected":1
    },
    {
        "experiment":"mml07",
        "acte":1,
        "scene":1,
        "version":"modern",
        "chunk":1,
        "verse_id":27,
        "char":"SGANARELLE",
        "text":"Mets-les par terre.",
        "selected":0
    },
    {
        "experiment":"mml07",
        "acte":1,
        "scene":1,
        "version":"modern",
        "chunk":2,
        "verse_id":27,
        "char":"SGANARELLE",
        "text":"Mets-les à terre.",
        "selected":0
    },
    {
        "experiment":"mml06",
        "acte":1,
        "scene":1,
        "version":"original",
        "chunk":4,
        "verse_id":27,
        "char":"SGANARELLE",
        "text":"Mets-les à terre.",
        "selected":0
    },
    {
        "experiment":"mml06",
        "acte":1,
        "scene":1,
        "version":"modern",
        "chunk":4,
        "verse_id":28,
        "char":"MARTINE",
        "text":"Tu penses vraiment que les choses peuvent continuer comme ça, ivrogne?...",
        "selected":0
    },
    {
        "experiment":"mml06",
        "acte":1,
        "scene":1,
        "version":"modern",
        "chunk":5,
        "verse_id":28,
        "char":"MARTINE",
        "text":"Ils me demandent du pain tout le temps.",
        "selected":1
    },
    {
        "experiment":"mml07",
        "acte":1,
        "scene":1,
        "version":"modern",
        "chunk":2,
        "verse_id":28,
        "char":"MARTINE",
        "text":"Ils me demandent du pain à toute heure.",
        "selected":0
    },
    {
        "experiment":"mml07",
        "acte":1,
        "scene":1,
        "version":"modern",
        "chunk":3,
        "verse_id":28,
        "char":"MARTINE",
        "text":"Ils me demandent du pain à n'importe quelle heure.",
        "selected":0
    },
    {
        "experiment":"mml06",
        "acte":1,
        "scene":1,
        "version":"original",
        "chunk":4,
        "verse_id":28,
        "char":"MARTINE",
        "text":"Qui me demandent à toute heure du pain.",
        "selected":0
    },
    {
        "experiment":"mml06",
        "acte":1,
        "scene":1,
        "version":"modern",
        "chunk":5,
        "verse_id":29,
        "char":"SGANARELLE",
        "text":"Donne-leur une fessée. Quand j'ai bien mangé et bu, je veux que tout le monde soit ivre dans ma maison.",
        "selected":1
    },
    {
        "experiment":"mml07",
        "acte":1,
        "scene":1,
        "version":"modern",
        "chunk":2,
        "verse_id":29,
        "char":"SGANARELLE",
        "text":"Donne-leur le fouet. Quand j'ai bien bu et bien mangé, je veux que tout le monde soit ivre dans ma maison.",
        "selected":0
    },
    {
        "experiment":"mml07",
        "acte":1,
        "scene":1,
        "version":"modern",
        "chunk":3,
        "verse_id":29,
        "char":"SGANARELLE",
        "text":"Donne-leur une correction. Quand j'ai bien mangé et bien bu, je veux que tout le monde soit ivre dans ma maison.",
        "selected":0
    },
    {
        "experiment":"mml06",
        "acte":1,
        "scene":1,
        "version":"original",
        "chunk":4,
        "verse_id":29,
        "char":"SGANARELLE",
        "text":"Donne-leur le fouet. Quand j'ai bien bu et bien mangé, je veux que tout le monde soit saoul dans ma maison.",
        "selected":0
    },
    {
        "experiment":"mml06",
        "acte":1,
        "scene":1,
        "version":"modern",
        "chunk":5,
        "verse_id":30,
        "char":"MARTINE",
        "text":"Tu penses vraiment que les choses peuvent continuer comme ça, toi l'ivrogne?",
        "selected":0
    },
    {
        "experiment":"mml07",
        "acte":1,
        "scene":1,
        "version":"modern",
        "chunk":2,
        "verse_id":30,
        "char":"MARTINE",
        "text":"Et tu prétends, ivrogne, que les choses restent toujours ainsi?...",
        "selected":0
    },
    {
        "experiment":"mml07",
        "acte":1,
        "scene":1,
        "version":"modern",
        "chunk":3,
        "verse_id":30,
        "char":"MARTINE",
        "text":"Et tu prétends, alcoolique, que les choses restent toujours les mêmes?...",
        "selected":0
    },
    {
        "experiment":"mml_manual",
        "acte":1,
        "scene":1,
        "version":"modern",
        "chunk":0,
        "verse_id":30,
        "char":"MARTINE",
        "text":"Et tu prétends, ivrogne, que les choses vont continuer comme ça ?",
        "selected":1
    },
    {
        "experiment":"mml06",
        "acte":1,
        "scene":1,
        "version":"original",
        "chunk":4,
        "verse_id":30,
        "char":"MARTINE",
        "text":"Et tu prétends, ivrogne, que les choses aillent toujours de même?...",
        "selected":0
    },
    {
        "experiment":"mml06",
        "acte":1,
        "scene":1,
        "version":"modern",
        "chunk":5,
        "verse_id":31,
        "char":"SGANARELLE",
        "text":"Ma chère femme, calme-toi s'il te plaît.",
        "selected":0
    },
    {
        "experiment":"mml06",
        "acte":1,
        "scene":1,
        "version":"modern",
        "chunk":6,
        "verse_id":31,
        "char":"SGANARELLE",
        "text":"Doucement, ma chérie, ne t'énerve pas.",
        "selected":1
    },
    {
        "experiment":"mml07",
        "acte":1,
        "scene":1,
        "version":"modern",
        "chunk":2,
        "verse_id":31,
        "char":"SGANARELLE",
        "text":"Ma femme, calmons-nous, s'il te plaît.",
        "selected":0
    },
    {
        "experiment":"mml06",
        "acte":1,
        "scene":1,
        "version":"original",
        "chunk":5,
        "verse_id":31,
        "char":"SGANARELLE",
        "text":"Ma femme, allons tout doucement, s'il vous plaît.",
        "selected":0
    },
    {
        "experiment":"mml06",
        "acte":1,
        "scene":1,
        "version":"modern",
        "chunk":5,
        "verse_id":32,
        "char":"MARTINE",
        "text":"Je dois supporter tes insultes et tes excès pour toujours?",
        "selected":0
    },
    {
        "experiment":"mml06",
        "acte":1,
        "scene":1,
        "version":"modern",
        "chunk":6,
        "verse_id":32,
        "char":"MARTINE",
        "text":"Tu crois que je vais supporter tes insultes et tes mauvaises actions pour toujours ?",
        "selected":1
    },
    {
        "experiment":"mml07",
        "acte":1,
        "scene":1,
        "version":"modern",
        "chunk":2,
        "verse_id":32,
        "char":"MARTINE",
        "text":"Je dois supporter éternellement tes insolences et tes débauches?...",
        "selected":0
    },
    {
        "experiment":"mml07",
        "acte":1,
        "scene":1,
        "version":"modern",
        "chunk":3,
        "verse_id":32,
        "char":"MARTINE",
        "text":"Est-ce que je dois supporter éternellement tes insolences et tes débauches?...",
        "selected":0
    },
    {
        "experiment":"mml06",
        "acte":1,
        "scene":1,
        "version":"original",
        "chunk":5,
        "verse_id":32,
        "char":"MARTINE",
        "text":"Que j'endure éternellement tes insolences et tes débauches?...",
        "selected":0
    },
    {
        "experiment":"mml06",
        "acte":1,
        "scene":1,
        "version":"modern",
        "chunk":5,
        "verse_id":33,
        "char":"SGANARELLE",
        "text":"Ne t'emporte pas, ma femme.",
        "selected":0
    },
    {
        "experiment":"mml06",
        "acte":1,
        "scene":1,
        "version":"modern",
        "chunk":6,
        "verse_id":33,
        "char":"SGANARELLE",
        "text":"Calme-toi, ma femme.",
        "selected":0
    },
    {
        "experiment":"mml07",
        "acte":1,
        "scene":1,
        "version":"modern",
        "chunk":2,
        "verse_id":33,
        "char":"SGANARELLE",
        "text":"Ne nous emportons pas, ma femme.",
        "selected":0
    },
    {
        "experiment":"mml_manual",
        "acte":1,
        "scene":1,
        "version":"modern",
        "chunk":0,
        "verse_id":33,
        "char":"SGANARELLE",
        "text":"Calme-toi, ma chérie.",
        "selected":1
    },
    {
        "experiment":"mml06",
        "acte":1,
        "scene":1,
        "version":"original",
        "chunk":5,
        "verse_id":33,
        "char":"SGANARELLE",
        "text":"Ne nous emportons point, ma femme.",
        "selected":0
    },
    {
        "experiment":"mml06",
        "acte":1,
        "scene":1,
        "version":"modern",
        "chunk":5,
        "verse_id":34,
        "char":"MARTINE",
        "text":"Et je ne peux pas trouver un moyen de te faire agir correctement?",
        "selected":1
    },
    {
        "experiment":"mml06",
        "acte":1,
        "scene":1,
        "version":"modern",
        "chunk":6,
        "verse_id":34,
        "char":"MARTINE",
        "text":"Et je ne sais pas comment te faire respecter tes devoirs ?",
        "selected":0
    },
    {
        "experiment":"mml07",
        "acte":1,
        "scene":1,
        "version":"modern",
        "chunk":2,
        "verse_id":34,
        "char":"MARTINE",
        "text":"Et je ne peux pas trouver un moyen de te faire revenir à tes devoirs?",
        "selected":0
    },
    {
        "experiment":"mml07",
        "acte":1,
        "scene":1,
        "version":"modern",
        "chunk":3,
        "verse_id":34,
        "char":"MARTINE",
        "text":"Et est-ce que je ne peux pas trouver un moyen de te faire revenir à tes devoirs?",
        "selected":0
    },
    {
        "experiment":"mml07",
        "acte":1,
        "scene":1,
        "version":"modern",
        "chunk":4,
        "verse_id":34,
        "char":"MARTINE",
        "text":"Et je ne sais pas comment te convaincre de faire ton devoir?",
        "selected":0
    },
    {
        "experiment":"mml06",
        "acte":1,
        "scene":1,
        "version":"original",
        "chunk":5,
        "verse_id":34,
        "char":"MARTINE",
        "text":"Et que je ne sache pas trouver le moyen de te ranger à ton devoir?",
        "selected":0
    },
    {
        "experiment":"mml06",
        "acte":1,
        "scene":1,
        "version":"modern",
        "chunk":5,
        "verse_id":35,
        "char":"SGANARELLE",
        "text":"Ma femme, tu sais que je ne suis pas patient et que je suis assez fort.",
        "selected":0
    },
    {
        "experiment":"mml06",
        "acte":1,
        "scene":1,
        "version":"modern",
        "chunk":6,
        "verse_id":35,
        "char":"SGANARELLE",
        "text":"Tu sais bien que je ne suis pas patient et que je suis assez fort.",
        "selected":0
    },
    {
        "experiment":"mml07",
        "acte":1,
        "scene":1,
        "version":"modern",
        "chunk":3,
        "verse_id":35,
        "char":"SGANARELLE",
        "text":"Ma femme, tu sais que je ne suis pas patient, et que je suis assez fort.",
        "selected":0
    },
    {
        "experiment":"mml_manual",
        "acte":1,
        "scene":1,
        "version":"modern",
        "chunk":0,
        "verse_id":35,
        "char":"SGANARELLE",
        "text":"Ma chérie, tu sais bien que je ne suis pas patient et que je suis assez fort.",
        "selected":1
    },
    {
        "experiment":"mml06",
        "acte":1,
        "scene":1,
        "version":"original",
        "chunk":5,
        "verse_id":35,
        "char":"SGANARELLE",
        "text":"Ma femme, vous savez que je n'ai pas l'âme endurante, et que j'ai le bras assez bon.",
        "selected":0
    },
    {
        "experiment":"mml06",
        "acte":1,
        "scene":1,
        "version":"modern",
        "chunk":6,
        "verse_id":36,
        "char":"MARTINE",
        "text":"Je me moque de tes menaces.",
        "selected":0
    },
    {
        "experiment":"mml06",
        "acte":1,
        "scene":1,
        "version":"modern",
        "chunk":7,
        "verse_id":36,
        "char":"MARTINE",
        "text":"Je me fiche de ce que tu dis.",
        "selected":0
    },
    {
        "experiment":"mml07",
        "acte":1,
        "scene":1,
        "version":"modern",
        "chunk":2,
        "verse_id":36,
        "char":"MARTINE",
        "text":"Je me moque de tes menaces.",
        "selected":0
    },
    {
        "experiment":"mml06",
        "acte":1,
        "scene":1,
        "version":"original",
        "chunk":6,
        "verse_id":36,
        "char":"MARTINE",
        "text":"Je me moque de tes menaces.",
        "selected":1
    },
    {
        "experiment":"mml06",
        "acte":1,
        "scene":1,
        "version":"modern",
        "chunk":6,
        "verse_id":37,
        "char":"SGANARELLE",
        "text":"Mon amour, ta peau te démange, comme d'habitude.",
        "selected":1
    },
    {
        "experiment":"mml06",
        "acte":1,
        "scene":1,
        "version":"modern",
        "chunk":7,
        "verse_id":37,
        "char":"SGANARELLE",
        "text":"Ma chérie, tu as l'habitude de te gratter la peau.",
        "selected":0
    },
    {
        "experiment":"mml07",
        "acte":1,
        "scene":1,
        "version":"modern",
        "chunk":3,
        "verse_id":37,
        "char":"SGANARELLE",
        "text":"Ma chère moitié, tu as envie de me voler quelque chose.",
        "selected":0
    },
    {
        "experiment":"mml07",
        "acte":1,
        "scene":1,
        "version":"modern",
        "chunk":4,
        "verse_id":37,
        "char":"SGANARELLE",
        "text":"Ma chérie, tu as toujours envie de te battre.",
        "selected":0
    },
    {
        "experiment":"mml06",
        "acte":1,
        "scene":1,
        "version":"original",
        "chunk":6,
        "verse_id":37,
        "char":"SGANARELLE",
        "text":"Ma petite femme, ma mie, votre peau vous démange, à votre ordinaire.",
        "selected":0
    },
    {
        "experiment":"mml06",
        "acte":1,
        "scene":1,
        "version":"modern",
        "chunk":6,
        "verse_id":38,
        "char":"MARTINE",
        "text":"Je vais te montrer que je ne te crains pas du tout.",
        "selected":0
    },
    {
        "experiment":"mml06",
        "acte":1,
        "scene":1,
        "version":"modern",
        "chunk":7,
        "verse_id":38,
        "char":"MARTINE",
        "text":"Je vais te prouver que je ne te crains pas du tout.",
        "selected":1
    },
    {
        "experiment":"mml07",
        "acte":1,
        "scene":1,
        "version":"modern",
        "chunk":3,
        "verse_id":38,
        "char":"MARTINE",
        "text":"Crois-tu que j'ai peur de tes paroles?",
        "selected":0
    },
    {
        "experiment":"mml07",
        "acte":1,
        "scene":1,
        "version":"modern",
        "chunk":4,
        "verse_id":38,
        "char":"MARTINE",
        "text":"Je te montrerai bien que je ne te crains pas du tout.",
        "selected":0
    },
    {
        "experiment":"mml06",
        "acte":1,
        "scene":1,
        "version":"original",
        "chunk":6,
        "verse_id":38,
        "char":"MARTINE",
        "text":"Je te montrerai bien que je ne te crains nullement.",
        "selected":0
    },
    {
        "experiment":"mml06",
        "acte":1,
        "scene":1,
        "version":"modern",
        "chunk":6,
        "verse_id":39,
        "char":"SGANARELLE",
        "text":"Ma chère moitié, tu veux me voler quelque chose.",
        "selected":0
    },
    {
        "experiment":"mml06",
        "acte":1,
        "scene":1,
        "version":"modern",
        "chunk":7,
        "verse_id":39,
        "char":"SGANARELLE",
        "text":"Mon amour, tu veux me voler quelque chose.",
        "selected":0
    },
    {
        "experiment":"mml07",
        "acte":1,
        "scene":1,
        "version":"modern",
        "chunk":3,
        "verse_id":39,
        "char":"SGANARELLE",
        "text":"Doux objet de mes désirs, je vais te donner une correction.",
        "selected":0
    },
    {
        "experiment":"mml07",
        "acte":1,
        "scene":1,
        "version":"modern",
        "chunk":4,
        "verse_id":39,
        "char":"SGANARELLE",
        "text":"Ma chère moitié, tu veux me voler quelque chose.",
        "selected":1
    },
    {
        "experiment":"mml06",
        "acte":1,
        "scene":1,
        "version":"original",
        "chunk":6,
        "verse_id":39,
        "char":"SGANARELLE",
        "text":"Ma chère moitié, vous avez envie de me dérober quelque chose.",
        "selected":0
    },
    {
        "experiment":"mml06",
        "acte":1,
        "scene":1,
        "version":"modern",
        "chunk":6,
        "verse_id":40,
        "char":"MARTINE",
        "text":"Tu penses que je vais avoir peur de tes paroles ?",
        "selected":0
    },
    {
        "experiment":"mml06",
        "acte":1,
        "scene":1,
        "version":"modern",
        "chunk":7,
        "verse_id":40,
        "char":"MARTINE",
        "text":"Tu crois que tes paroles me font peur?",
        "selected":1
    },
    {
        "experiment":"mml07",
        "acte":1,
        "scene":1,
        "version":"modern",
        "chunk":3,
        "verse_id":40,
        "char":"MARTINE",
        "text":"Alcoolique que tu es!",
        "selected":0
    },
    {
        "experiment":"mml07",
        "acte":1,
        "scene":1,
        "version":"modern",
        "chunk":4,
        "verse_id":40,
        "char":"MARTINE",
        "text":"Crois-tu que tes paroles me font peur?",
        "selected":0
    },
    {
        "experiment":"mml06",
        "acte":1,
        "scene":1,
        "version":"original",
        "chunk":6,
        "verse_id":40,
        "char":"MARTINE",
        "text":"Crois-tu que je m'épouvante de tes paroles?",
        "selected":0
    },
    {
        "experiment":"mml06",
        "acte":1,
        "scene":1,
        "version":"modern",
        "chunk":7,
        "verse_id":41,
        "char":"SGANARELLE",
        "text":"Mon cher objet de désir, je vais te frotter les oreilles.",
        "selected":0
    },
    {
        "experiment":"mml06",
        "acte":1,
        "scene":1,
        "version":"modern",
        "chunk":8,
        "verse_id":41,
        "char":"SGANARELLE",
        "text":"Je vais te donner une correction, tu vas voir.",
        "selected":0
    },
    {
        "experiment":"mml07",
        "acte":1,
        "scene":1,
        "version":"modern",
        "chunk":3,
        "verse_id":41,
        "char":"SGANARELLE",
        "text":"Je vais te battre.",
        "selected":0
    },
    {
        "experiment":"mml07",
        "acte":1,
        "scene":1,
        "version":"modern",
        "chunk":4,
        "verse_id":41,
        "char":"SGANARELLE",
        "text":"Doux objet de mes désirs, je vais te donner une correction.",
        "selected":1
    },
    {
        "experiment":"mml06",
        "acte":1,
        "scene":1,
        "version":"original",
        "chunk":7,
        "verse_id":41,
        "char":"SGANARELLE",
        "text":"Doux objet de mes voeux, je vous frotterai les oreilles.",
        "selected":0
    },
    {
        "experiment":"mml06",
        "acte":1,
        "scene":1,
        "version":"modern",
        "chunk":7,
        "verse_id":42,
        "char":"MARTINE",
        "text":"Tu es un ivrogne!",
        "selected":0
    },
    {
        "experiment":"mml06",
        "acte":1,
        "scene":1,
        "version":"modern",
        "chunk":8,
        "verse_id":42,
        "char":"MARTINE",
        "text":"Tu es complètement ivre!",
        "selected":0
    },
    {
        "experiment":"mml07",
        "acte":1,
        "scene":1,
        "version":"modern",
        "chunk":3,
        "verse_id":42,
        "char":"MARTINE",
        "text":"Sac à vin!",
        "selected":0
    },
    {
        "experiment":"mml07",
        "acte":1,
        "scene":1,
        "version":"modern",
        "chunk":4,
        "verse_id":42,
        "char":"MARTINE",
        "text":"Ivrogne que tu es!",
        "selected":0
    },
    {
        "experiment":"mml_manual",
        "acte":1,
        "scene":1,
        "version":"modern",
        "chunk":0,
        "verse_id":42,
        "char":"MARTINE",
        "text":"Ivrogne!",
        "selected":1
    },
    {
        "experiment":"mml06",
        "acte":1,
        "scene":1,
        "version":"original",
        "chunk":7,
        "verse_id":42,
        "char":"MARTINE",
        "text":"Ivrogne que tu es!",
        "selected":0
    },
    {
        "experiment":"mml06",
        "acte":1,
        "scene":1,
        "version":"modern",
        "chunk":7,
        "verse_id":43,
        "char":"SGANARELLE",
        "text":"Je vais te frapper.",
        "selected":1
    },
    {
        "experiment":"mml06",
        "acte":1,
        "scene":1,
        "version":"modern",
        "chunk":8,
        "verse_id":43,
        "char":"SGANARELLE",
        "text":"Je vais te frapper.",
        "selected":0
    },
    {
        "experiment":"mml07",
        "acte":1,
        "scene":1,
        "version":"modern",
        "chunk":3,
        "verse_id":43,
        "char":"SGANARELLE",
        "text":"Je vais te donner une raclée.",
        "selected":0
    },
    {
        "experiment":"mml06",
        "acte":1,
        "scene":1,
        "version":"original",
        "chunk":7,
        "verse_id":43,
        "char":"SGANARELLE",
        "text":"Je vous battrai.",
        "selected":0
    },
    {
        "experiment":"mml06",
        "acte":1,
        "scene":1,
        "version":"modern",
        "chunk":7,
        "verse_id":44,
        "char":"MARTINE",
        "text":"Tu es un sac à vin!",
        "selected":0
    },
    {
        "experiment":"mml06",
        "acte":1,
        "scene":1,
        "version":"modern",
        "chunk":8,
        "verse_id":44,
        "char":"MARTINE",
        "text":"Tu es un alcoolique!",
        "selected":0
    },
    {
        "experiment":"mml07",
        "acte":1,
        "scene":1,
        "version":"modern",
        "chunk":4,
        "verse_id":44,
        "char":"MARTINE",
        "text":"Sac à vin!",
        "selected":1
    },
    {
        "experiment":"mml06",
        "acte":1,
        "scene":1,
        "version":"original",
        "chunk":7,
        "verse_id":44,
        "char":"MARTINE",
        "text":"Sac à vin!",
        "selected":0
    },
    {
        "experiment":"mml06",
        "acte":1,
        "scene":1,
        "version":"modern",
        "chunk":7,
        "verse_id":45,
        "char":"SGANARELLE",
        "text":"Je vais te donner une correction.",
        "selected":0
    },
    {
        "experiment":"mml06",
        "acte":1,
        "scene":1,
        "version":"modern",
        "chunk":8,
        "verse_id":45,
        "char":"SGANARELLE",
        "text":"Je vais te battre.",
        "selected":1
    },
    {
        "experiment":"mml07",
        "acte":1,
        "scene":1,
        "version":"modern",
        "chunk":4,
        "verse_id":45,
        "char":"SGANARELLE",
        "text":"Je vais te battre.",
        "selected":0
    },
    {
        "experiment":"mml06",
        "acte":1,
        "scene":1,
        "version":"original",
        "chunk":7,
        "verse_id":45,
        "char":"SGANARELLE",
        "text":"Je vous rosserai.",
        "selected":0
    },
    {
        "experiment":"mml06",
        "acte":1,
        "scene":1,
        "version":"modern",
        "chunk":8,
        "verse_id":46,
        "char":"MARTINE",
        "text":"Tu es un misérable!",
        "selected":0
    },
    {
        "experiment":"mml07",
        "acte":1,
        "scene":1,
        "version":"modern",
        "chunk":4,
        "verse_id":46,
        "char":"MARTINE",
        "text":"Misérable!",
        "selected":1
    },
    {
        "experiment":"mml06",
        "acte":1,
        "scene":1,
        "version":"original",
        "chunk":8,
        "verse_id":46,
        "char":"MARTINE",
        "text":"Infime!",
        "selected":0
    },
    {
        "experiment":"mml06",
        "acte":1,
        "scene":1,
        "version":"modern",
        "chunk":8,
        "verse_id":47,
        "char":"SGANARELLE",
        "text":"Je vais te punir.",
        "selected":0
    },
    {
        "experiment":"mml07",
        "acte":1,
        "scene":1,
        "version":"modern",
        "chunk":4,
        "verse_id":47,
        "char":"SGANARELLE",
        "text":"Je vais te donner une raclée.",
        "selected":1
    },
    {
        "experiment":"mml06",
        "acte":1,
        "scene":1,
        "version":"original",
        "chunk":8,
        "verse_id":47,
        "char":"SGANARELLE",
        "text":"Je vous étrillerai.",
        "selected":0
    },
    {
        "experiment":"mml06",
        "acte":1,
        "scene":1,
        "version":"modern",
        "chunk":8,
        "verse_id":48,
        "char":"MARTINE",
        "text":"Traître, insolent, menteur, lâche, escroc, vaurien, malhonnête, filou, brigand, voleur!...",
        "selected":1
    },
    {
        "experiment":"mml07",
        "acte":1,
        "scene":1,
        "version":"modern",
        "chunk":4,
        "verse_id":48,
        "char":"MARTINE",
        "text":"Traître, insolent, trompeur, lâche, coquin, pendard, gueux, bélître, fripon, maraud, voleur!...",
        "selected":0
    },
    {
        "experiment":"mml06",
        "acte":1,
        "scene":1,
        "version":"original",
        "chunk":8,
        "verse_id":48,
        "char":"MARTINE",
        "text":"Traître, insolent, trompeur, lâche, coquin, pendard, gueux, bélître, fripon, maraut, voleur!...",
        "selected":0
    },
    {
        "experiment":"mml06",
        "acte":1,
        "scene":1,
        "version":"modern",
        "chunk":8,
        "verse_id":49,
        "char":"SGANARELLE",
        "text":"(Il prend un bâton et le lui donne.) Tu veux te battre?",
        "selected":0
    },
    {
        "experiment":"mml07",
        "acte":1,
        "scene":1,
        "version":"modern",
        "chunk":4,
        "verse_id":49,
        "char":"SGANARELLE",
        "text":"(Il prend un bâton et lui en donne.) Ah! Tu en veux donc?",
        "selected":1
    },
    {
        "experiment":"mml06",
        "acte":1,
        "scene":1,
        "version":"original",
        "chunk":8,
        "verse_id":49,
        "char":"SGANARELLE",
        "text":"(Il prend un bâton, et lui en donne.) Ah! vous en voulez donc?",
        "selected":0
    },
    {
        "experiment":"mml06",
        "acte":1,
        "scene":1,
        "version":"modern",
        "chunk":8,
        "verse_id":50,
        "char":"MARTINE",
        "text":"Ah! ah! ah! ah!",
        "selected":0
    },
    {
        "experiment":"mml06",
        "acte":1,
        "scene":1,
        "version":"original",
        "chunk":8,
        "verse_id":50,
        "char":"MARTINE",
        "text":"Ah! ah! ah! ah!",
        "selected":1
    },
    {
        "experiment":"mml07",
        "acte":1,
        "scene":1,
        "version":"modern",
        "chunk":4,
        "verse_id":51,
        "char":"SGANARELLE",
        "text":"Voilà le vrai moyen de te calmer.",
        "selected":1
    },
    {
        "experiment":"mml07",
        "acte":1,
        "scene":1,
        "version":"original",
        "chunk":4,
        "verse_id":51,
        "char":"SGANARELLE",
        "text":"Voilà le vrai moyen de vous apaiser.",
        "selected":0
    }
]